{
  "main": {
    "id": "1d9f5115778402f1",
    "type": "split",
    "children": [
      {
        "id": "427721b7c2daf159",
        "type": "tabs",
        "children": [
          {
            "id": "561278952577f6a4",
            "type": "leaf",
            "state": {
              "type": "markdown",
              "state": {
                "file": "Introduction Into Machine Learning🤖🧠🚀.md",
                "mode": "source",
                "source": false
              },
              "icon": "lucide-file",
              "title": "Introduction Into Machine Learning🤖🧠🚀"
            }
          },
          {
            "id": "ee8003f7dd2d47be",
            "type": "leaf",
            "state": {
              "type": "graph",
              "state": {},
              "icon": "lucide-git-fork",
              "title": "Graph view"
            }
          }
        ],
        "currentTab": 1
      }
    ],
    "direction": "vertical"
  },
  "left": {
    "id": "bc29c080b53ee8c4",
    "type": "split",
    "children": [
      {
        "id": "ba42e6d313a08672",
        "type": "tabs",
        "children": [
          {
            "id": "16fe81a25c2b622f",
            "type": "leaf",
            "state": {
              "type": "file-explorer",
              "state": {
                "sortOrder": "alphabetical"
              },
              "icon": "lucide-folder-closed",
              "title": "Files"
            }
          },
          {
            "id": "448da50567091da0",
            "type": "leaf",
            "state": {
              "type": "search",
              "state": {
                "query": "",
                "matchingCase": false,
                "explainSearch": false,
                "collapseAll": false,
                "extraContext": false,
                "sortOrder": "alphabetical"
              },
              "icon": "lucide-search",
              "title": "Search"
            }
          },
          {
            "id": "de169e8be7d3549c",
            "type": "leaf",
            "state": {
              "type": "bookmarks",
              "state": {},
              "icon": "lucide-bookmark",
              "title": "Bookmarks"
            }
          }
        ]
      }
    ],
    "direction": "horizontal",
    "width": 300
  },
  "right": {
    "id": "c2ebb6aa22f743b8",
    "type": "split",
    "children": [
      {
        "id": "fda5ef355eee3b04",
        "type": "tabs",
        "children": [
          {
            "id": "f72afcc068beaf5e",
            "type": "leaf",
            "state": {
              "type": "backlink",
              "state": {
                "collapseAll": false,
                "extraContext": false,
                "sortOrder": "alphabetical",
                "showSearch": false,
                "searchQuery": "",
                "backlinkCollapsed": false,
                "unlinkedCollapsed": true
              },
              "icon": "links-coming-in",
              "title": "Backlinks"
            }
          },
          {
            "id": "c38fd274c0edd3ea",
            "type": "leaf",
            "state": {
              "type": "outgoing-link",
              "state": {
                "linksCollapsed": false,
                "unlinkedCollapsed": true
              },
              "icon": "links-going-out",
              "title": "Outgoing links"
            }
          },
          {
            "id": "80b4fa7182eb0706",
            "type": "leaf",
            "state": {
              "type": "tag",
              "state": {
                "sortOrder": "frequency",
                "useHierarchy": true
              },
              "icon": "lucide-tags",
              "title": "Tags"
            }
          },
          {
            "id": "203358e71bf68b87",
            "type": "leaf",
            "state": {
              "type": "outline",
              "state": {},
              "icon": "lucide-list",
              "title": "Outline"
            }
          }
        ]
      }
    ],
    "direction": "horizontal",
    "width": 300,
    "collapsed": true
  },
  "left-ribbon": {
    "hiddenItems": {
      "switcher:Open quick switcher": false,
      "graph:Open graph view": false,
      "canvas:Create new canvas": false,
      "daily-notes:Open today's daily note": false,
      "templates:Insert template": false,
      "command-palette:Open command palette": false,
      "obsidian-git:Open Git source control": false
    }
  },
  "active": "ee8003f7dd2d47be",
  "lastOpenFiles": [
    "Introduction Into Machine Learning🤖🧠🚀.md",
    "Main Component of Machine Learning⚙️.md",
    "Assets/machine_learning_algorithm.png",
    "Assets/high-lelvel-machine-learning-process.png",
    "Assets/Feature-Engineering.png",
    "Assets/dataexample.jpeg",
    "README.md",
    "Assets/MLdiagram.png",
    "Assets/traditional programming.png",
    "Assets/ai_taxonomy.jpeg",
    "Assets",
    "Welcome.md"
  ]
}